<dolfin nsmap="{'dolfin': 'https://fenicsproject.org/'}">
  <mesh celltype="triangle" dim="3">
    <vertices size="12">
      <vertex index="0" x="0.0" y="0.0" z="0.0" />
      <vertex index="1" x="2.0" y="0.0" z="0.0" />
      <vertex index="2" x="0.0" y="2.0" z="0.0" />
      <vertex index="3" x="2.0" y="2.0" z="0.0" />
      <vertex index="4" x="0.999999999997388" y="0.0" z="0.0" />
      <vertex index="5" x="2.0" y="0.999999999997388" z="0.0" />
      <vertex index="6" x="1.000000000004118" y="2.0" z="0.0" />
      <vertex index="7" x="0.0" y="1.000000000004118" z="0.0" />
      <vertex index="8" x="0.5875000000009173" y="1.412500000000833" z="0.0" />
      <vertex index="9" x="0.7499999999991589" y="0.7500000000008413" z="0.0" />
      <vertex index="10" x="1.295833333333814" y="1.28749999999968" z="0.0" />
      <vertex index="11" x="1.437499999998692" y="0.5624999999990218" z="0.0" />
    </vertices>
    <cells size="14">
      <triangle index="0" v0="5" v1="3" v2="10" />
      <triangle index="1" v0="7" v1="0" v2="9" />
      <triangle index="2" v0="0" v1="4" v2="9" />
      <triangle index="3" v0="3" v1="6" v2="10" />
      <triangle index="4" v0="4" v1="1" v2="11" />
      <triangle index="5" v0="1" v1="5" v2="11" />
      <triangle index="6" v0="6" v1="2" v2="8" />
      <triangle index="7" v0="2" v1="7" v2="8" />
      <triangle index="8" v0="5" v1="10" v2="11" />
      <triangle index="9" v0="8" v1="7" v2="9" />
      <triangle index="10" v0="8" v1="9" v2="10" />
      <triangle index="11" v0="9" v1="4" v2="11" />
      <triangle index="12" v0="10" v1="9" v2="11" />
      <triangle index="13" v0="6" v1="8" v2="10" />
    </cells>
  </mesh>
</dolfin>